toncli/__init__.py
toncli/config.ini
toncli/main.py
toncli/lib/fift-libs/Asm.fif
toncli/lib/fift-libs/AsmTests.fif
toncli/lib/fift-libs/Color.fif
toncli/lib/fift-libs/Fift.fif
toncli/lib/fift-libs/GetOpt.fif
toncli/lib/fift-libs/Lisp.fif
toncli/lib/fift-libs/Lists.fif
toncli/lib/fift-libs/Stack.fif
toncli/lib/fift-libs/TonUtil.fif
toncli/lib/func-libs/error_codes.func
toncli/lib/func-libs/math.func
toncli/lib/func-libs/stdlib.func
toncli/lib/test-libs/1.address_helpers.func
toncli/lib/test-libs/bad_messages_generator.func
toncli/lib/test-libs/c5_parse_helpers.func
toncli/lib/test-libs/message_helpers.func
toncli/lib/test-libs/storage-test-helpers.func
toncli/lib/test-libs/tests-helpers.func
toncli/lib/test-libs/token-helpers.func
toncli/modules/__init__.py
toncli/modules/deploy_contract.py
toncli/modules/deploy_wallet_contract.py
toncli/modules/projects.py
toncli/modules/abstract/__init__.py
toncli/modules/abstract/deployer.py
toncli/modules/fift/cli.fif.template
toncli/modules/fift/contract_manipulation.fif
toncli/modules/fift/data_proxy.fif.template
toncli/modules/fift/deploy-wallet.fif
toncli/modules/fift/fift_tests.fif.template.fif
toncli/modules/fift/get_run.fif.template
toncli/modules/fift/run_test.fif.template
toncli/modules/fift/run_test_old.fif.template
toncli/modules/fift/transaction_debug.fif.template
toncli/modules/utils/__init__.py
toncli/modules/utils/check_hash.py
toncli/modules/utils/transaction.py
toncli/modules/utils/commands/__init__.py
toncli/modules/utils/commands/commands_executer.py
toncli/modules/utils/commands/command_classes/__init__.py
toncli/modules/utils/commands/command_classes/addrs_command.py
toncli/modules/utils/commands/command_classes/build_cli_libs_command.py
toncli/modules/utils/commands/command_classes/deploy_command.py
toncli/modules/utils/commands/command_classes/func_or_fc_or_build_command.py
toncli/modules/utils/commands/command_classes/get_command.py
toncli/modules/utils/commands/command_classes/help_or_h_command.py
toncli-0.0.43.dist-info/LICENSE
toncli-0.0.43.dist-info/METADATA
toncli-0.0.43.dist-info/WHEEL
toncli-0.0.43.dist-info/entry_points.txt
toncli-0.0.43.dist-info/top_level.txt
toncli-0.0.43.dist-info/RECORD
