Metadata-Version: 2.1
Name: toncli
Version: 0.0.43
Summary: Easy to use CLI for fift / func projects
Home-page: https://github.com/disintar/toncli
Author: Andrey Tvorozhkov
Author-email: andrey@head-labs.com
Project-URL: Bug Tracker, https://github.com/disintar/toncli/issues
Classifier: Programming Language :: Python :: 3
Classifier: License :: OSI Approved :: Apple Public Source License
Classifier: Operating System :: OS Independent
Classifier: Environment :: Console
Requires-Python: >=3.8
License-File: LICENSE
Requires-Dist: colorama
Requires-Dist: appdirs
Requires-Dist: requests
Requires-Dist: pyyaml
Requires-Dist: Jinja2
Requires-Dist: bitstring
